c2log/__init__.py
c2log/fields.py
c2log/logbook.py
c2log/structures/__init__.py
c2log/structures/base.py
c2log/structures/fixed.py
c2log/structures/interval.py
c2log/structures/user.py
c2log/structures/variable.py
c2log-0.1.1.dist-info/DESCRIPTION.rst
c2log-0.1.1.dist-info/LICENSE.txt
c2log-0.1.1.dist-info/METADATA
c2log-0.1.1.dist-info/RECORD
c2log-0.1.1.dist-info/WHEEL
c2log-0.1.1.dist-info/metadata.json
c2log-0.1.1.dist-info/top_level.txt
