Metadata-Version: 2.0
Name: c2log
Version: 0.1.1
Summary: Library for parsing log files generated by Concept2 rowers.
Home-page: http://gitlab.com/rmoe/c2log
Author: Ryan Moe
Author-email: ryan.moe@gmail.com
License: GPLv3
Platform: UNKNOWN
Classifier: Development Status :: 4 - Beta
Classifier: Programming Language :: Python :: 3.4
Classifier: Programming Language :: Python :: 3.5
Classifier: Programming Language :: Python :: 3.6
Classifier: License :: OSI Approved :: GNU General Public License v3 (GPLv3)
Requires-Dist: suitcase
